ziggof1broadcasts/__init__.py
ziggof1broadcasts-0.1.0.dist-info/LICENSE
ziggof1broadcasts-0.1.0.dist-info/LICENSE.md
ziggof1broadcasts-0.1.0.dist-info/METADATA
ziggof1broadcasts-0.1.0.dist-info/WHEEL
ziggof1broadcasts-0.1.0.dist-info/top_level.txt
ziggof1broadcasts-0.1.0.dist-info/RECORD
